{
    "task": [
        {
            "id": "d6d670a1-06b2-46a3-977e-3d9b651a2bb1",
            "title": "MongoDB",
            "description": "Aprender MongoDB para conseguir primeira vaga",
            "created_at": "2024-07-29T01:02:53.636Z",
            "completed_at": null,
            "updated_at": "2024-07-29T01:02:53.636Z"
        },
        {
            "id": "8c523a9d-e6e8-42d1-8fc7-6ee07a79a203",
            "title": "Task 01",
            "description": "Descrição da Task 01",
            "created_at": "2024-07-29T01:02:57.840Z",
            "completed_at": null,
            "updated_at": "2024-07-29T01:02:57.840Z"
        },
        {
            "id": "b85b0cf9-1ae9-4a0d-9a5f-3e604aaa4a68",
            "title": "Task 02",
            "description": "Descrição da Task 02",
            "created_at": "2024-07-29T01:02:57.841Z",
            "completed_at": null,
            "updated_at": "2024-07-29T01:02:57.841Z"
        },
        {
            "id": "e554c07f-45e6-4074-bc5c-690b62b731c7",
            "title": "Task 03",
            "description": "Descrição da Task 03",
            "created_at": "2024-07-29T01:02:57.842Z",
            "completed_at": null,
            "updated_at": "2024-07-29T01:02:57.842Z"
        },
        {
            "id": "d6cb13e8-8d10-4739-8d9e-513879fe2556",
            "title": "Task 04",
            "description": "Descrição da Task 04",
            "created_at": "2024-07-29T01:02:57.843Z",
            "completed_at": null,
            "updated_at": "2024-07-29T01:02:57.843Z"
        },
        {
            "id": "af66645a-8dab-461a-afb6-b2c4dff28f60",
            "title": "Task 05",
            "description": "Descrição da Task 05",
            "created_at": "2024-07-29T01:02:57.843Z",
            "completed_at": null,
            "updated_at": "2024-07-29T01:02:57.843Z"
        }
    ]
}
